contextlocal/__init__.py
contextlocal/local.py
contextlocal/py.typed
contextlocal-0.1.2.dist-info/LICENSE
contextlocal-0.1.2.dist-info/METADATA
contextlocal-0.1.2.dist-info/WHEEL
contextlocal-0.1.2.dist-info/RECORD
